[
  {
    "content": "# DESLIZAMENTOS # Como agir? # DEFESA CIVIL # JOINVILLE - SC # Conhe\u00e7a seu terreno: - Verifique se sua casa est\u00e1 em \u00e1rea de risco (encostas, \u00e1reas de v\u00e1rzea, etc.). - Observe se h\u00e1 rachaduras no solo, muros ou paredes. - Identifique se h\u00e1 \u00e1rvores inclinadas ou com ra\u00edzes expostas. # Como agir antes? 1. # Prepare sua casa - N\u00e3o construa em \u00e1reas de risco. - Se sua casa estiver em \u00e1rea de risco, reforce muros de conten\u00e7\u00e3o e fa\u00e7a drenagem adequada do terreno. - N\u00e3o retire a vegeta\u00e7\u00e3o natural das encostas. 2. # Fique atento - Acompanhe as previs\u00f5es meteorol\u00f3gicas. - Observe se h\u00e1 sinais de deslizamento (rachaduras, inclina\u00e7\u00e3o de \u00e1rvores, etc.). - Mantenha contato com a Defesa Civil e \u00f3rg\u00e3os competentes. # DEFESA CIVIL # JOINVILLE - SC # Como agir durante? 1. Saia de casa - Se perceber sinais de deslizamento, saia de casa imediatamente. - Avise seus vizinhos sobre o perigo. - Leve documentos importantes, \u00e1gua, alimentos n\u00e3o perec\u00edveis e medicamentos. 2.",
    "index": 0,
    "start_char": 0,
    "end_char": 962,
    "metadata": {
      "url": "https://www.joinville.sc.gov.br/wp-content/uploads/2025/04/Cartilha-Deslizamentos-como-agir.pdf",
      "url_hash": "ad72c20edb9842ed",
      "chunked_at": "2025-06-03T19:08:04.570646",
      "document_type": "guide",
      "disaster_category": "landslide",
      "information_type": "preparation",
      "target_audience": "family",
      "urgency_level": "medium",
      "disaster_phase": "before",
      "region": null,
      "state": null,
      "area_type": "general",
      "source_authority": null,
      "authority_level": "federal",
      "has_emergency_contacts": false,
      "has_instructions": false,
      "has_maps": true,
      "confidence_score": 0.6,
      "extraction_timestamp": "2025-06-03T19:08:04.570314",
      "chunk_index": 0,
      "total_chunks": 2,
      "section_type": "procedures",
      "instruction_density": 0.023809523809523808
    }
  },
  {
    "content": "Saia de casa - Se perceber sinais de deslizamento, saia de casa imediatamente. - Avise seus vizinhos sobre o perigo. - Leve documentos importantes, \u00e1gua, alimentos n\u00e3o perec\u00edveis e medicamentos. 2. Procure abrigo - Abrigue-se em local seguro, longe de \u00e1reas de risco. - Se estiver na rua, procure um local alto e firme. - Evite \u00e1reas de encosta e rios. DEFESA CIVIL JOINVILLE - SC # Como agir depois? 1. Verifique a seguran\u00e7a - N\u00e3o volte para casa at\u00e9 que as autoridades garantam a seguran\u00e7a do local. - Verifique se h\u00e1 riscos de novos deslizamentos. - Inspecione sua casa e veja se h\u00e1 danos. 2. Ajude o pr\u00f3ximo - Ajude seus vizinhos em caso de necessidade. - Entre em contato com as autoridades para informar sobre os danos. Defesa Civil: 199 Bombeiros: 193 Pol\u00edcia Militar: 190 SAMU: 192 # DEFESA CIVIL # JOINVILLE - SC",
    "index": 1,
    "start_char": 765,
    "end_char": 1586,
    "metadata": {
      "url": "https://www.joinville.sc.gov.br/wp-content/uploads/2025/04/Cartilha-Deslizamentos-como-agir.pdf",
      "url_hash": "ad72c20edb9842ed",
      "chunked_at": "2025-06-03T19:08:04.570646",
      "document_type": "guide",
      "disaster_category": "landslide",
      "information_type": "preparation",
      "target_audience": "family",
      "urgency_level": "medium",
      "disaster_phase": "before",
      "region": null,
      "state": null,
      "area_type": "general",
      "source_authority": null,
      "authority_level": "federal",
      "has_emergency_contacts": true,
      "has_instructions": false,
      "has_maps": true,
      "confidence_score": 0.6,
      "extraction_timestamp": "2025-06-03T19:08:04.570314",
      "chunk_index": 1,
      "total_chunks": 2,
      "section_type": "procedures",
      "instruction_density": 0.02054794520547945
    }
  }
]